awmt/basic_python_package/__init__.py
awmt/basic_python_package/example.py
awmt_basic_python_packge-0.1.1.dist-info/LICENSE
awmt_basic_python_packge-0.1.1.dist-info/METADATA
awmt_basic_python_packge-0.1.1.dist-info/WHEEL
awmt_basic_python_packge-0.1.1.dist-info/RECORD
